hw_package_amishayash/__init__.py
hw_package_amishayash/__main__.py
hw_package_amishayash/assertions.py
hw_package_amishayash/runner.py
hw_package_amishayash-0.0.7.dist-info/LICENSE.txt
hw_package_amishayash-0.0.7.dist-info/METADATA
hw_package_amishayash-0.0.7.dist-info/WHEEL
hw_package_amishayash-0.0.7.dist-info/top_level.txt
hw_package_amishayash-0.0.7.dist-info/RECORD
