Metadata-Version: 2.1
Name: hw-package-amishayash
Version: 0.0.7
Summary: First Package made by Amisha and Yash
Home-page: UNKNOWN
Author: yash19130 (Yash Tanwar)
Author-email: <yash19130@iiitd.ac.in>
License: UNKNOWN
Keywords: python,tests,package,assertions,runner,os
Platform: UNKNOWN
Classifier: Development Status :: 1 - Planning
Classifier: Intended Audience :: Developers
Classifier: Programming Language :: Python :: 3
Classifier: Operating System :: Unix
Classifier: Operating System :: MacOS :: MacOS X
Classifier: Operating System :: Microsoft :: Windows
License-File: LICENSE.txt
